{"Symbols":["about","approval","approve","automatic","biohazard","cancel","checkmark","collapse","collect","copyleft","copyright","currency_exchange","dislike","expand","high_priority","info","like","like_placeholder","minus","next","ok","plus","previous","rating","registered_trademark","service_mark","sound_recording_copyright","start","synchronize","trademark"],"Technical and software":["accept_database","add_column","add_database","add_row","address_book","alphabetical_sorting_az","alphabetical_sorting_za","audio_file","bookmark","broken_link","capacitor","cell_phone","charge_battery","circuit","clear_filters","command_line","comments","crystal_oscillator","cursor","data_backup","data_configuration","data_encryption","data_protection","data_recovery","data_sheet","database","delete_column","delete_database","delete_row","download","edit_image","electrical_sensor","electrical_threshold","electro_devices","electronics","empty_battery","empty_filter","empty_trash","engineering","export","feed_in","file","filled_filter","folder","full_battery","full_trash","genealogy","generic_sorting_asc","generic_sorting_desc","headset","high_battery","integrated_webcam","landscape","link","lock","lock_landscape","lock_portrait","low_battery","menu","middle_battery","missed_call","mms","multiple_devices","multiple_inputs","multiple_smartphones","numerical_sorting_12","numerical_sorting_21","opened_folder","parallel_tasks","phone","print","privacy","redo","refresh","search","serial_tasks","settings","share","sim_card","sim_card_chip","smartphone_tablet","sms","speaker","touchscreen_smartphone","tree_structure","two_smartphones","undo","unlock","upload","video_call","voicemail"],"Film and Photography":["add_image","camcorder","camcorder_pro","camera","camera_addon","camera_identification","clapperboard","close_up_mode","compact_camera","film","film_reel","flash_auto","flash_off","flash_on","frame","gallery","image_file","multiple_cameras","no_video","old_time_camera","panorama","photo_reel","picture","remove_image","rotate_camera","rotate_to_landscape","rotate_to_portrait","slr_back_side","stack_of_photos","switch_camera","video_file","video_projector","webcam"],"Arrows":["advance","down","down_left","down_right","left","left_down","left_down2","left_up","left_up2","right","right_down","right_down2","right_up","right_up2","up","up_left","up_right"],"Time":["alarm_clock","calendar","clock","leave","planner"],"Business":["answers","area_chart","bad_decision","bar_chart","bearish","briefcase","bullish","business","business_contact","calculator","call_transfer","callback","collaboration","combo_chart","conference_call","contacts","decision","department","deployment","disapprove","disclaimer","document","donate","doughnut_chart","end_call","expired","external","factory","factory_breakdown","faq","feedback","filing_cabinet","fine_print","flow_chart","good_decision","grid","heat_map","idea","import","in_transit","inspection","internal","invite","line_chart","list","low_priority","make_decision","medium_priority","mind_map","money_transfer","negative_dynamic","neutral_decision","neutral_trading","no_idea","org_unit","organization","overtime","package","paid","pie_chart","positive_dynamic","process","questions","radar_plot","ratings","safe","sales_performance","scatter_plot","self_service_kiosk","services","shipped","statistics","support","survey","template","timeline","todo_list","view_details","vip","workflow"],"People and activities":["assistant","businessman","businesswoman","butting_in","customer_support","debt","manager","night_portrait","online_support","podium_with_speaker","portrait_mode","reading","reading_ebook","reuse","selfie","sports_mode","voice_presentation"],"":["automotive","binoculars","candle_sticks","cloth","dam","display","do_not_inhale","do_not_insert","do_not_mix","electricity","globe","home","key","light_at_the_end_of_tunnel","music","news","night_landscape","puzzle","shop","signature"],"Academic":["biomass","biotech","diploma_1","diploma_2","graduation_cap","library","podium_with_audience","podium_without_speaker","ruler","rules"]}